django_svg_sprite/__init__.py
django_svg_sprite/apps.py
django_svg_sprite/conf.py
django_svg_sprite/templatetags/__init__.py
django_svg_sprite/templatetags/svg_sprite.py
django_svg_sprite/tests/__init__.py
django_svg_sprite/tests/settings.py
django_svg_sprite/tests/test_templatetags.py
django_svg_sprite-2025.12.3.dist-info/licenses/LICENSE
django_svg_sprite-2025.12.3.dist-info/METADATA
django_svg_sprite-2025.12.3.dist-info/WHEEL
django_svg_sprite-2025.12.3.dist-info/RECORD
