Metadata-Version: 2.4
Name: django-svg-sprite
Version: 2025.12.3
Summary: A Django template tag for easy use of SVG sprites in templates.
License-Expression: MIT
License-File: LICENSE
Author: Tobias Bölz
Author-email: tobias@boelz.eu
Requires-Python: >=3.10,<4.0
Classifier: Environment :: Web Environment
Classifier: Framework :: Django
Classifier: Intended Audience :: Developers
Classifier: License :: OSI Approved :: MIT License
Classifier: Operating System :: OS Independent
Classifier: Programming Language :: Python
Classifier: Programming Language :: Python :: 3
Classifier: Programming Language :: Python :: 3 :: Only
Classifier: Programming Language :: Python :: 3.10
Classifier: Programming Language :: Python :: 3.11
Classifier: Programming Language :: Python :: 3.12
Classifier: Programming Language :: Python :: 3.13
Classifier: Programming Language :: Python :: 3.14
Classifier: Topic :: Internet :: WWW/HTTP
Classifier: Topic :: Internet :: WWW/HTTP :: Dynamic Content
Requires-Dist: django (>=4.2)
Project-URL: Changelog, https://tmb.codeberg.page/django-svg-sprite/changelog/
Project-URL: Documentation, https://tmb.codeberg.page/django-svg-sprite/
Project-URL: Homepage, https://tmb.codeberg.page/django-svg-sprite/
Project-URL: Issues, https://git.boelz.eu/tmb/django-svg-sprite/issues
Project-URL: Repository, https://git.boelz.eu/tmb/django-svg-sprite
